FortniteAPI/FortniteAPI.py
FortniteAPI/Stats.py
FortniteAPI/__init__.py
FortniteTrackerAPI-0.0.1.dist-info/METADATA
FortniteTrackerAPI-0.0.1.dist-info/RECORD
FortniteTrackerAPI-0.0.1.dist-info/WHEEL
FortniteTrackerAPI-0.0.1.dist-info/top_level.txt
